setup.py
speakin_gender_sdk/__init__.py
speakin_gender_sdk/api_client.py
speakin_gender_sdk/configuration.py
speakin_gender_sdk/rest.py
speakin_gender_sdk.egg-info/PKG-INFO
speakin_gender_sdk.egg-info/SOURCES.txt
speakin_gender_sdk.egg-info/dependency_links.txt
speakin_gender_sdk.egg-info/requires.txt
speakin_gender_sdk.egg-info/top_level.txt
speakin_gender_sdk/apis/__init__.py
speakin_gender_sdk/apis/genderreleasev_api.py
speakin_gender_sdk/models/__init__.py
test/__init__.py
test/test_genderreleasev_api.py