Metadata-Version: 1.0
Name: speakin-gender-sdk
Version: 1.0.0
Summary: gender_release_v1
Home-page: UNKNOWN
Author: UNKNOWN
Author-email: UNKNOWN
License: UNKNOWN
Keywords: Swagger,gender_release_v1
Platform: UNKNOWN
